cleanslay/__init__.py
cleanslay/json_sanitizer.py
cleanslay-0.1.0.dist-info/licenses/LICENSE
cleanslay-0.1.0.dist-info/METADATA
cleanslay-0.1.0.dist-info/WHEEL
cleanslay-0.1.0.dist-info/top_level.txt
cleanslay-0.1.0.dist-info/RECORD
