Metadata-Version: 2.4
Name: cleanslay
Version: 0.1.0
Summary: Safe JSON serializer for complex Python objects (Pydantic, Pandas, NumPy, etc.)
Home-page: https://github.com/grakn/cleanslay
Author: Pragman
Author-email: Phragman <a@staphi.com>
License-Expression: MIT
Requires-Python: >=3.7
License-File: LICENSE
Provides-Extra: test
Requires-Dist: pytest; extra == "test"
Requires-Dist: numpy; extra == "test"
Requires-Dist: pandas; extra == "test"
Requires-Dist: pydantic; extra == "test"
Dynamic: author
Dynamic: home-page
Dynamic: license-file
Dynamic: requires-python
